{
  "date_str": "2019-07-19",
  "decision_num": 19,
  "title": "Procurement for the supply of 45,000 vials of 5g - 6g of Human Immunoglobulin required for Intravenous use",
  "source_url": "https://www.cabinetoffice.gov.lk/cab/index.php?option=com_content&view=article&id=16&Itemid=49&lang=en&dID=9941",
  "decision_details": "- The proposal made by the Minister of Health, Nutrition & Indigenous Medicine, to award the procurement for the supply of 45,000 vials of 5g - 6g of Human Immunoglobulin required for Intravenous use, to M/s Reliance Life Science (Pvt.) Ltd. of India for a sum of US$ 4.8 million, as recommended by the Standing Cabinet Appointed Procurement Committee (SCAPC), was approved by the Cabinet.",
  "key": "2019-07-19-019-71cf"
}