{
  "key": "2025-01-27-007-3302",
  "title": "Holding the Fourth Ministerial Conference of the Institution of Regional Integrated Multi Hazard Early Warning System (RIMES)",
  "source_url": "https://www.cabinetoffice.gov.lk/cab/index.php?option=com_content&view=article&id=16&Itemid=49&lang=en&dID=13007",
  "decision_details": "- The Regional Integrated Multi Hazard Early Warning System (RIMES) is an institution affiliated to the United Nations Organization with a membership of more than 40 countries in Asia, Africa and the Pacific Region.  The objective of RIMES is to assist and provide technical expertise to the member States for the enhancement of early warning technical strategies in relation to disasters such as floods, droughts, landslides and cyclones which impact the member States. A request has been made to hold the Fourth Ministerial Conference of RIMES in Sri Lanka in 2025.  Accordingly, the proposal made by the Minister of Agriculture, Livestock, Land and Irrigation to hold the Fourth Ministerial Conference of the Institution of Regional Integrated Multi Hazard Early Warning System (RIMES) in Colombo during the last week of April or the first week of May 2025 for four days, was approved by the Cabinet.",
  "date_str": "2025-01-27",
  "decision_num": 7
}