{
  "date_str": "2018-08-07",
  "decision_num": 4,
  "title": "Signing of Terms of Reference of the Joint Russian - Sri Lankan Working group on Military - Technical Cooperation",
  "source_url": "https://www.cabinetoffice.gov.lk/cab/index.php?option=com_content&view=article&id=16&Itemid=49&lang=en&dID=9059",
  "decision_details": "- The proposal made by H.E. the President Maithripala Sirisena, in his capacity as  the Minister of Defence, to sign the Terms of Reference containing the  functions and conditions of  the Joint Russian - Sri Lankan Working group on Military - Technical Cooperation proposed to be established as per the Agreement  on Military - Technical Cooperation signed between Russian Federation and Sri Lanka in 2004, was approved by the Cabinet.",
  "key": "2018-08-07-004-c095"
}