{
  "date_str": "2017-02-14",
  "decision_num": 16,
  "title": "Procurement of Food Items (raw, dry rations and various other items) required for the Three Armed Services",
  "source_url": "https://www.cabinetoffice.gov.lk/cab/index.php?option=com_content&view=article&id=16&Itemid=49&lang=en&dID=7491",
  "decision_details": "- The proposal made by H.E. the President Maithripala Sirisena, in his capacity as the Minister of Defence, to award the contracts for the procurement of food items (raw, dry rations and various other items) required for the Three Armed Services for the year 2017, to 28 suppliers for a total sum of Rs.17,555 Million, as recommended by the Standing Cabinet Appointed Procurement Committee (SCAPC),was approved by the Cabinet.",
  "key": "2017-02-14-016-854d"
}