{
  "date_str": "2014-09-18",
  "decision_num": 18,
  "title": "Nagamu Purawara 2014 - Third Phase Renovation of Multi-storeyed Housing Schemes and installing Infrastructure Facilities",
  "source_url": "https://www.cabinetoffice.gov.lk/cab/index.php?option=com_content&view=article&id=16&Itemid=49&lang=en&dID=5713",
  "decision_details": "- the Government has allocated Rs. 1878 Million to the National Housing Development Authority for the modernization of Multi?storeyed Housing Schemes and provision of infrastructure facilities. It is expected to carry out renovation work of the following 12 housing schemes under the 3rd phase of \u201cNagamu Purawara\u201d:\r\n\r\n\t\t*\tSaunders Place Housing Scheme \t\t-\t57 houses;\r\n\t\t*\tAnderson Housing Scheme \t\t-        816 house;\r\n\t\t*\t117 Watta - Elvitigala Housing  Scheme \r\n\t\t\tfor low income earners \t\t\t-\t32 houses;\r\n\t\t*\tKandawalawatta Housing Scheme\t-\t72 houses;\r\n\t\t*\tMayura Place Housing Scheme - \r\n\t\t\tWellawatta\t\t\t\t\t-\t24 houses;\r\n\t\t*\tTorrington New Housing Scheme -\r\n\t\t\tPhase IV\t\t\t\t\t-\t48 houses;\r\n\t\t*\t797 Watta Housing Scheme (Phase II)\t-        116 houses;\r\n\t\t*\tVipulasena Mawatha Housing Scheme,\t-\t52 houses \r\n\t\t\tShops and Office complex\t\t\t\tand\r\n\t\t\t\t\t\t\t\t\t \t20 shops\r\n\t\t*\tRestoring drain system, Mahawatta\t-\t20 houses;\r\n\t\t*\tSt Anthony's Housing Scheme - \r\n\t\t\tKollupitiya\t\t\t\t\t-\t64 houses;\r\n\t\t*\tMattegoda Housing Scheme\t\t-      1122 houses; and\r\n\t\t*\tRanpokunagama Housing Scheme -\r\n\t\t\tCompleting the remaining work of the \r\n\t\t\tsewage treatment plant\t\t\t-        322 houses",
  "key": "2014-09-18-018-3ece"
}