{
  "date_str": "2020-11-30",
  "decision_num": 3,
  "title": "Submission of the published Gazette Extraordinary Notifications to Parliament for approval",
  "source_url": "https://www.cabinetoffice.gov.lk/cab/index.php?option=com_content&view=article&id=16&Itemid=49&lang=en&dID=10761",
  "decision_details": "- The proposal made by the Hon. Prime Minister in his capacity as the Minister of Finance to submit six Gazette Extraordinary Notifications published under the Special Commodity Levy Act, No.48 of 2007, one Gazette Extraordinary Notification published under the Revenue Protection Act, No.19 of 1962 and one Gazette Extraordinary Notification issued in respect of imposing Surcharge on customs import duty for imported fuel in terms of the provisions of Customs Ordinance, to Parliament, was approved by the Cabinet.",
  "key": "2020-11-30-003-58cb"
}