{
  "date_str": "2024-01-08",
  "decision_num": 3,
  "title": "Establishment of a University of Science and Teachnology in Sri Lanka",
  "source_url": "https://www.cabinetoffice.gov.lk/cab/index.php?option=com_content&view=article&id=16&Itemid=49&lang=en&dID=12347",
  "decision_details": "- With the objective of preparing the foundation to create a cadre of skilled\tprofessionals to take the leadership in critical sectors of new scientific \tdiscoveries, technological  innovation and sustainable development, it has been \tidentified the appropriateness of establishing a University of Science and \tTechnology in collaboration with a renowned university in United States of \tAmerica. Such a university will cater to utilize cutting-edge methodologies, \tfoster global \tacademic connections and create an environment for research and \tdevelopment. The  proposal made by the Hon. President to select one partner \tuniversity from among several identified universities including UC Berkeley, \tUC Riverside, UC Davis, University of Michigan and establish the proposed \tUniversity of Science and Technology as a Public-Private Partnership in \tcollaboration with the said university, was approved by the Cabinet.",
  "key": "2024-01-08-003-6a2c"
}