{
  "date_str": "2024-03-11",
  "decision_num": 6,
  "title": "Establishment of 100MW, Oddamawadi, Baticaloa Solar Power Project on \tBuild, Own and Operate basis",
  "source_url": "https://www.cabinetoffice.gov.lk/cab/index.php?option=com_content&view=article&id=16&Itemid=49&lang=en&dID=12440",
  "decision_details": "- Approval of the Cabinet has been granted at the meeting held on 2021\u201108-30 to call for Expressions of Interest for the renewable energy development with a capacity of 50 MW or above of various renewable energy technologies. Accordingly, taking into consideration the Expressions of Interest received,  the proposal made by the Minister of Power and Energy to award the  project for the establishment of a Solar Power Project of 100MW at Oddamawadi, Baticaloa on Build, Own and Operate basis, with an operational period of 20 years, to Solar Forge Batticaloa, as per the recommendation of the Standing Cabinet Appointed Negotiating Committee, was approved by the Cabinet.",
  "key": "2024-03-11-006-df85"
}