{
  "date_str": "2011-04-06",
  "decision_num": 8,
  "title": "Strengthening the patient care services of District General Hospital - Hambantota, District Hospital - Tissamaharama and Base Hospital - Karawanella by providing essential Medical Equipment",
  "source_url": "https://www.cabinetoffice.gov.lk/cab/index.php?option=com_content&view=article&id=16&Itemid=49&lang=en&dID=3955",
  "decision_details": "- on a proposal made by Hon.Maithripala Sirisena, Minister of Health, Cabinet approval was granted to sign the commercial contract of this project.  Provision of these equipment to the hospitals will provide better health care services to the people living in the relevant areas.",
  "key": "2011-04-06-008-a39a"
}