{
  "date_str": "2014-01-13",
  "decision_num": 9,
  "title": "International Conference on Natural Fibers in Collaboration with Food & Agriculture Organization of the United Nations (FAO)",
  "source_url": "https://www.cabinetoffice.gov.lk/cab/index.php?option=com_content&view=article&id=16&Itemid=49&lang=en&dID=5361",
  "decision_details": "- this Conference was held in Sri Lanka in November 2013 with the participation of 47 delegates from Member Countries. As the host country, Sri Lanka was offered Chairmanship of the Inter-Governmental Group on Natural Fibres for the next 02 years. Sri Lanka being the World's Second Largest Exporter of coir products is presently going for more value added production in the fibre sector.  The above information provided by Hon. Jagath Pushpakumara, Minister of Coconut Development and Janatha Estate Development, was noted by the Cabinet.",
  "key": "2014-01-13-009-1ad9"
}