{
  "date_str": "2013-11-11",
  "decision_num": 3,
  "title": "Transfer of 80 P Land at Mudun Ela, Kelaniya to the National Water Supply and Drainage Board",
  "source_url": "https://www.cabinetoffice.gov.lk/cab/index.php?option=com_content&view=article&id=16&Itemid=49&lang=en&dID=5278",
  "decision_details": "- the proposal made by H.E. the President, in his capacity as the Minister of Defence and Urban Development, to allocate the above block of land through the Sri Lanka Land Reclamation and Development Corporation to the National Water Supply and Drainage Board for the construction of the Engineer's office for Kelaniya/Peliyagoda area, with the view to providing a better service with required facilities to the people in the area, was approved by the Cabinet.",
  "key": "2013-11-11-003-f441"
}