{
  "key": "2025-06-09-007-86dd",
  "title": "Allocation of provisions for the projects identified in the industrial and enterprise development sectors",
  "source_url": "https://www.cabinetoffice.gov.lk/cab/index.php?option=com_content&view=article&id=16&Itemid=49&lang=en&dID=13222",
  "decision_details": "- Policy and other decisions required to uplift the existing status of the Small Enterprises Development Division, Industrial Development Board, Lanka Salusala Ltd, Ceylon Ceramics Corporation and the Export Development Board are being implemented with the intervention of those Institutions/divisions and the Ministry of Industry and Entrepreneurship Development utilizing the staff, natural resources, machinery and other physical resources of those institutions/divisions. Accordingly, the proposal made by the Minister of Industry and Entrepreneurship Development to allocate Rs. 100 million from the provisions allocated for the year 2025 under the Sectoral Development Programme of the Ministry of Industry and Entrepreneurship Development for the following projects was approved by the Cabinet.* Reality Show Programme organized by the Small Enterprises Development Division.* Industry Expo Exhibition organized by Industrial Development Board.* Pilot project to establish a revolving fund to provide raw materials required for local textile production at subsidized prices.* Providing working capital to the Ceylon Ceramics Corporation.* Purchase of scanners to introduce Advanced Scanner Technology to the inspection yard (Security Checkpoint at Cargo Village) maintained\u00a0 by the Industrial Development Board at the premises of Bandaranaike International Airport, Katunayake.",
  "date_str": "2025-06-09",
  "decision_num": 7
}