{
  "date_str": "2024-06-19",
  "decision_num": 8,
  "title": "Paving works of Jaya Container Terminal-V Yard in the Colombo Port",
  "source_url": "https://www.cabinetoffice.gov.lk/cab/index.php?option=com_content&view=article&id=16&Itemid=49&lang=en&dID=12599",
  "decision_details": "- Plans relating to the paving of the Jaya Container Terminal - V of the Colombo Port have been prepared by the Sri Lanka Ports Authority. Accordingly, the proposal made by the Minister of Ports, Shipping and Aviation to call for National Competitive Bids and select a suitable institution for this work, and to appoint a Cabinet Appointed Procurement Committee and a Technical Evaluation Committee, was approved by the Cabinet.",
  "key": "2024-06-19-008-aca6"
}