{
  "date_str": "2019-12-04",
  "decision_num": 5,
  "title": "Appointment of Secretaries to the State Ministries",
  "source_url": "https://www.cabinetoffice.gov.lk/cab/index.php?option=com_content&view=article&id=16&Itemid=49&lang=en&dID=10284",
  "decision_details": "- The proposal made by H.E. the President  for the appointment of  Secretaries to State Ministries of the the newly appointed State Ministers under Article 44(1) of the Constitution of the Democratic Socialist Republic of Sri Lanka, was approved by the Cabinet.",
  "key": "2019-12-04-005-42ab"
}