{
  "date_str": "2011-08-24",
  "decision_num": 1,
  "title": "Implementation of water supply facilities for Deyata Kirula National Development Programme & Exhibition, 2012",
  "source_url": "https://www.cabinetoffice.gov.lk/cab/index.php?option=com_content&view=article&id=16&Itemid=49&lang=en&dID=4157",
  "decision_details": "- this programme is to be held in Oyamaduwa area, in Mahavilachchiya, Anuradhapura. A land area of about 500 acres belonging to the National Livestock Development Board is to be used for the exhibition.  The proposal made by Hon. Dinesh Gunawardena, Minister of Water Supply and Drainage for the development of water supply facilities in and around the Deyata Kirula Exhibition area and in all Divisional Secretariats in Anuradhapura District as well, at a cost of Rs.830 million to be expended during 2011 and 2012, was approved by the Cabinet.  This project will provide safe drinking water to 6100 families in the area.",
  "key": "2011-08-24-001-cb51"
}