{
  "date_str": "2021-02-22",
  "decision_num": 6,
  "title": "Expansion of the Kalutara Industrial Estate",
  "source_url": "https://www.cabinetoffice.gov.lk/cab/index.php?option=com_content&view=article&id=16&Itemid=49&lang=en&dID=10942",
  "decision_details": "- The Kalutara Industrial Estate has been set up in a land in extent of 50 acres called \u201cPullerton Estate\u201d and at present, 33 investors have set up factories and its commercial production activities are successfully being carried out. Those investors have invested at around Rs. 837 million and have provided about 775 job opportunities. Although both local and foreign investors have forwarded to set up industries in the western province, no land blocks remain in any of the 08 industrial estates set up in the western province. Taking these into consideration, the proposal made by the Minister of Industries to release the Government owned land in extent of 1.946 hectares located adjacent to the Kalutara Industrial Estate  to expand the said industrial estate and to allocate such lands to the industrialists under the Regional Industrial Estate Development Programme, having fulfilled required infrastructure facilities, was approved by the Cabinet.",
  "key": "2021-02-22-006-bdd9"
}