{
  "date_str": "2015-03-18",
  "decision_num": 14,
  "title": "Second Phase of the renovation of the Superior Courts Complex Building",
  "source_url": "https://www.cabinetoffice.gov.lk/cab/index.php?option=com_content&view=article&id=16&Itemid=49&lang=en&dID=5996",
  "decision_details": "The Superior Courts Complex Building  where the Supreme Court, Appeals Court and the Ministry of Justice of the Democratic Socialist Republic of Sri Lanka are housed, was constructed by the Chinese Government in the decade of 1980 and on a request made by the Government of Sri Lanka to the Government of the Republic of China, the 1st phase of its renovations was  successfully completed in the years 2013 and 2014 as a free gift from the Chinese Government.  The proposal made by Hon. Wijayadasa Rajapaksha, Minister of Justice and Labour Relations, to enter into a preliminary Agreement with the Republic of China to bring a  specialized Chinese Team of Designers to the country to attend to initial designing of the following renovations as the second phase of the said renovations to be carried out as a gift from the  Chinese Government, was approved by the Cabinet: \r\n\r\n*\tstructural changes to the layout of the building \r\n*\trepairs to the entire electrical system \r\n*\trepairs to the drainage system \r\n*\trepairs to the telephone system \r\n*\trepairs to the fire guard system and \r\n*\trepairs to the air conditioning system",
  "key": "2015-03-18-014-9293"
}