{
  "date_str": "2016-06-07",
  "decision_num": 9,
  "title": "Purchasing of 42,000 Metric Tons of Urea by the two State Fertilizer Companies",
  "source_url": "https://www.cabinetoffice.gov.lk/cab/index.php?option=com_content&view=article&id=16&Itemid=49&lang=en&dID=6810",
  "decision_details": "- The proposal made by Hon. Duminda Dissanayake, the Minister of Agriculture, to purchase 42,000 Metric Tons of Urea through the two State Fertilizer Companies,  to continuously address the fertilizer requirements of the farmer community of the country, at a reasonable price, as per the recommendation of the Special Standing Cabinet Appointed Procurement Committee, was approved by the Cabinet.",
  "key": "2016-06-07-009-0e90"
}