{
  "date_str": "2014-12-17",
  "decision_num": 23,
  "title": "Proposed Training Centre to be constructed at Kotawilawatta, Matara in parallel to the 'Deyata Kirula' National Exhibition",
  "source_url": "https://www.cabinetoffice.gov.lk/cab/index.php?option=com_content&view=article&id=16&Itemid=49&lang=en&dID=5890",
  "decision_details": "- the proposal made by Hon. Chandrasiri Gajadeera, Minister of Rehabilitation and Prison Reforms, to construct the above training centre to be utilized as the training school for the officers of the Department of Prisons, was approved by the Cabinet.",
  "key": "2014-12-17-023-2e04"
}