{
  "date_str": "2019-02-26",
  "decision_num": 13,
  "title": "Presenting the Draft National Building Research Institute (NBRI) Bill in Parliament",
  "source_url": "https://www.cabinetoffice.gov.lk/cab/index.php?option=com_content&view=article&id=16&Itemid=49&lang=en&dID=9541",
  "decision_details": "- Approval of the Cabinet has been granted previously to draft a bill to establish the National Building Research Organization (NBRO) by an Act of Parliament. Accordingly, the proposal made by Hon. Ranjith Madduma Bandara, the Minister of Public Administration & Disaster Management, to publish the draft bill prepared accordingly in the Government Gazette and thereafter, present the same in Parliament for approval, was approved by the Cabinet.",
  "key": "2019-02-26-013-66cf"
}