{
  "date_str": "2021-09-06",
  "decision_num": 3,
  "title": "Providing relief for the difficulties faced by the Small and Medium Scale Enterprises",
  "source_url": "https://www.cabinetoffice.gov.lk/cab/index.php?option=com_content&view=article&id=16&Itemid=49&lang=en&dID=11232",
  "decision_details": "- Approval of the Cabinet was granted at its meeting held on 2020\u201110\u201126 to appoint an Officials' Committee to identify the difficulties faced by the Small and Medium Scale enterprises and submit recommendations on the relief to be provided to them and to propose  a mechanism for preparing a data base on the small and medium scale entrepreneurs. As such, the proposal made by the Minister of Industries to implement the recommendations submitted by the said Officials' Committee on the appropriate relief to be provided to the Small and Medium Scale entrepreneurs affected due to the COVID\u201119 Pandemic and Easter Sunday Attack, was approved by the Cabinet.",
  "key": "2021-09-06-003-8d64"
}