{
  "date_str": "2018-09-11",
  "decision_num": 2,
  "title": "Completion of the construction work of the Public Library Building in Batticaloa",
  "source_url": "https://www.cabinetoffice.gov.lk/cab/index.php?option=com_content&view=article&id=16&Itemid=49&lang=en&dID=9176",
  "decision_details": "- Construction work of a new building in place of the 50 year old building where the present Public Library of Batticaloa is located is now underway. As such, the proposal made by Hon. Ranil Wickremasinghe, the Prime Minister in his capacity as the Minister of National Policies and Economic Affairs, to secure Rs.169.97 million required further to complete the construction work of the said building from the Budget of the  year 2019, was approved by the Cabinet.",
  "key": "2018-09-11-002-5452"
}